CHANGELOG.md
MANIFEST.in
README.md
setup.cfg
setup.py
example/__init__.py
example/main.py
example/data/Dummy.py
example/data/DummySchema.py
example/data/__init__.py
example/logic/DummyCommandSet.py
example/logic/DummyController.py
example/logic/IDummyController.py
example/logic/__init__.py
example/services/DummyCommandableHttpService.py
example/services/DummyRestService.py
example/services/__init__.py
pip_services3_swagger/__init__.py
pip_services3_swagger.egg-info/PKG-INFO
pip_services3_swagger.egg-info/SOURCES.txt
pip_services3_swagger.egg-info/dependency_links.txt
pip_services3_swagger.egg-info/requires.txt
pip_services3_swagger.egg-info/top_level.txt
pip_services3_swagger.egg-info/zip-safe
pip_services3_swagger/__pycache__/__init__.cpython-38.pyc
pip_services3_swagger/build/DefaultSwaggerFactory.py
pip_services3_swagger/build/__init__.py
pip_services3_swagger/services/SwaggerService.py
pip_services3_swagger/services/__init__.py
pip_services3_swagger/services/__pycache__/SwaggerService.cpython-38.pyc
pip_services3_swagger/services/__pycache__/__init__.cpython-38.pyc
pip_services3_swagger/swagger-ui/favicon-16x16.png
pip_services3_swagger/swagger-ui/favicon-32x32.png
pip_services3_swagger/swagger-ui/index.html
pip_services3_swagger/swagger-ui/oauth2-redirect.html
pip_services3_swagger/swagger-ui/swagger-ui-bundle.js
pip_services3_swagger/swagger-ui/swagger-ui-bundle.js.map
pip_services3_swagger/swagger-ui/swagger-ui-es-bundle-core.js
pip_services3_swagger/swagger-ui/swagger-ui-es-bundle-core.js.map
pip_services3_swagger/swagger-ui/swagger-ui-es-bundle.js
pip_services3_swagger/swagger-ui/swagger-ui-es-bundle.js.map
pip_services3_swagger/swagger-ui/swagger-ui-standalone-preset.js
pip_services3_swagger/swagger-ui/swagger-ui-standalone-preset.js.map
pip_services3_swagger/swagger-ui/swagger-ui.css
pip_services3_swagger/swagger-ui/swagger-ui.css.map
pip_services3_swagger/swagger-ui/swagger-ui.js
pip_services3_swagger/swagger-ui/swagger-ui.js.map